oc_auth/__init__.py
oc_auth/http.py
oc_auth/kube_config.py
oc_auth/cli/__init__.py
oc_auth/cli/_base.py
oc_auth/cli/main.py
oc_replacement-0.3.3.dist-info/METADATA
oc_replacement-0.3.3.dist-info/WHEEL
oc_replacement-0.3.3.dist-info/entry_points.txt
oc_replacement-0.3.3.dist-info/top_level.txt
oc_replacement-0.3.3.dist-info/zip-safe
oc_replacement-0.3.3.dist-info/RECORD
