Metadata-Version: 2.1
Name: oc-replacement
Version: 0.3.3
Summary: A replacement for the OAuth flow for interacting with OpenShift-based Kubernetes clusters
Home-page: https://github.com/thelonelyghost/oc-auth
Author: David Alexander
Author-email: opensource@thelonelyghost.com
License: MIT
Platform: UNKNOWN
Classifier: Development Status :: 1 - Planning
Classifier: Intended Audience :: End Users/Desktop
Classifier: Programming Language :: Python :: 3
Classifier: Programming Language :: Python :: 3.7
Requires-Dist: ruamel.yaml
Requires-Dist: requests
Requires-Dist: requests-oauthlib
Provides-Extra: dev
Requires-Dist: pytest ; extra == 'dev'
Requires-Dist: pytest-cov ; extra == 'dev'
Requires-Dist: better-exceptions ; extra == 'dev'
